LICENSE
MANIFEST.in
README.md
setup.py
test.sh
pycataloguer/__init__.py
pycataloguer/cli.py
pycataloguer.egg-info/PKG-INFO
pycataloguer.egg-info/SOURCES.txt
pycataloguer.egg-info/dependency_links.txt
pycataloguer.egg-info/entry_points.txt
pycataloguer.egg-info/requires.txt
pycataloguer.egg-info/top_level.txt