Metadata-Version: 1.1
Name: pycataloguer
Version: 0.0.1
Summary: Cataloguer for your files
Home-page: https://github.com/shyzik93/PyCataloguer
Author: Konstantin Polyakov
Author-email: shyzik93@mail.ru
License: LGPL-3.0
Download-URL: https://github.com/shyzik93/pycataloguer/archive/master.zip
Platform: UNKNOWN
Classifier: Environment :: Console
Classifier: Natural Language :: English
Classifier: Programming Language :: Python :: 3.4
Classifier: Topic :: Scientific/Engineering
